LICENSE
MANIFEST.in
README.rst
setup.py
python_redis_log.egg-info/PKG-INFO
python_redis_log.egg-info/SOURCES.txt
python_redis_log.egg-info/dependency_links.txt
python_redis_log.egg-info/requires.txt
python_redis_log.egg-info/top_level.txt
redislog/__init__.py
redislog/handlers.py
redislog/logger.py