Metadata-Version: 1.0
Name: python-redis-log
Version: 0.1.2
Summary: Redis pub/sub logging handler for python
Home-page: https://github.com/jedp/python-redis-log
Author: Jed Parsons
Author-email: jed@jedparsons.com
License: MIT
Platform: UNKNOWN
